README.md
pyproject.toml
setup.py
pysrc/itcast_car.egg-info/PKG-INFO
pysrc/itcast_car.egg-info/SOURCES.txt
pysrc/itcast_car.egg-info/dependency_links.txt
pysrc/itcast_car.egg-info/not-zip-safe
pysrc/itcast_car.egg-info/top_level.txt
pysrc/itcast_tools/__init__.py
pysrc/itcast_tools/wifi.py
src/bindings.cpp
src/ctrl_service.cpp
src/video_service.cpp