Metadata-Version: 2.1
Name: itcast-car
Version: 0.0.1
Summary:  itcast wifi car, vision and control 
Home-page: UNKNOWN
Author: XQ
Author-email: xiaoqi@itcast.cn
License: MIT License
Platform: UNKNOWN
Classifier: Programming Language :: Python :: 3
Classifier: License :: OSI Approved :: MIT License
Classifier: Operating System :: OS Independent
Requires-Python: >=3.6
